eva/__init__.py
eva_jirakova-0.0.1.dist-info/LICENSE
eva_jirakova-0.0.1.dist-info/METADATA
eva_jirakova-0.0.1.dist-info/WHEEL
eva_jirakova-0.0.1.dist-info/top_level.txt
eva_jirakova-0.0.1.dist-info/RECORD
