Metadata-Version: 2.1
Name: eva-jirakova
Version: 0.0.1
Summary: EVA (Equation Visualisation Applet) displays and interlinks a set of equations.
Home-page: https://repo.tok.ipp.cas.cz/jirakova/eva
Author: Katerina Hromasova
Author-email: jirakova@ipp.cas.cz
License: UNKNOWN
Platform: UNKNOWN
Classifier: Programming Language :: Python :: 3
Classifier: License :: OSI Approved :: MIT License
Classifier: Operating System :: OS Independent
Requires-Python: >=3.6
Requires-Dist: numpy
Requires-Dist: scipy
Requires-Dist: xarray
